midtransclient/__init__.py
midtransclient/config.py
midtransclient/core_api.py
midtransclient/error_midtrans.py
midtransclient/http_client.py
midtransclient/snap.py
midtransclient/transactions.py
tests/__init__.py
tests/config.py
tests/context.py
tests/helpers.py
tests/test_config.py
tests/test_core_api.py
tests/test_http_client.py
tests/test_midtransclient.py
tests/test_snap.py
tests/test_subscription.py
tests/test_tokenization.py
midtransclient-1.4.2.dist-info/LICENSE
midtransclient-1.4.2.dist-info/METADATA
midtransclient-1.4.2.dist-info/WHEEL
midtransclient-1.4.2.dist-info/top_level.txt
midtransclient-1.4.2.dist-info/RECORD
