Metadata-Version: 2.1
Name: midtransclient
Version: 1.4.2
Summary: Official Midtrans Payment API Client
Home-page: https://github.com/midtrans/midtrans-python-client/
Author: Midtrans - Integration Support Team
Author-email: support@midtrans.com
License: MIT
Classifier: Programming Language :: Python
Classifier: Programming Language :: Python :: 3
Classifier: Programming Language :: Python :: 3 :: Only
Classifier: Programming Language :: Python :: 3.5
Classifier: Programming Language :: Python :: 3.6
Classifier: Programming Language :: Python :: 3.7
Classifier: Programming Language :: Python :: 3.8
Classifier: Programming Language :: Python :: 3.9
Classifier: Programming Language :: Python :: 3.10
Classifier: Topic :: Software Development :: Libraries :: Python Modules
Requires-Python: >=3.5
License-File: LICENSE
